LICENSE.txt
MANIFEST.in
README.txt
setup.py
triz2sce.py
triz2sce_func.py
triz2sce.egg-info/PKG-INFO
triz2sce.egg-info/SOURCES.txt
triz2sce.egg-info/dependency_links.txt
triz2sce.egg-info/top_level.txt