Metadata-Version: 1.2
Name: triz2sce
Version: 1.0
Summary: Convierte mapas de aventuras de texto generados por Trizbort en código fuente para el DAAD.
Home-page: http://www.zonafi.rockersuke.com/triz2sce/index.html
Author: Pedro Fernández
Author-email: rockersuke@gmail.com
License: MIT
Platform: UNKNOWN
Requires-Python: >=3.5
